rummikub_solver/__init__.py
rummikub_solver/_gamestate.py
rummikub_solver/_ruleset.py
rummikub_solver/_solver.py
rummikub_solver/_types.py
rummikub_solver/_utils.py
rummikub_solver/_version.py
rummikub_solver/py.typed
rummikub_solver-1.0.0.dist-info/METADATA
rummikub_solver-1.0.0.dist-info/WHEEL
rummikub_solver-1.0.0.dist-info/licenses/LICENSE.txt
rummikub_solver-1.0.0.dist-info/RECORD
