Metadata-Version: 2.4
Name: rummikub-solver
Version: 1.0.0
Summary: Rummikub solver library
Project-URL: Documentation, https://rummikub-solver.readthedocs.io
Project-URL: GitHub, https://github.com/mjpieters/rummikub-solver
Project-URL: Issues, https://github.com/mjpieters/rummikub-solver/issues
Project-URL: Changelog, https://github.com/mjpieters/rummikub-solver/blob/main/CHANGELOG.md
Author-email: Martijn Pieters <mj@zopatista.com>
License-Expression: MIT
License-File: LICENSE.txt
Classifier: Development Status :: 5 - Production/Stable
Classifier: License :: OSI Approved :: MIT License
Classifier: Programming Language :: Python
Classifier: Programming Language :: Python :: 3
Classifier: Programming Language :: Python :: Implementation :: CPython
Classifier: Topic :: Games/Entertainment :: Board Games
Requires-Python: >=3.11
Requires-Dist: cvxpy-base>=1.3.0
Requires-Dist: numpy
Provides-Extra: cbc
Requires-Dist: cylp; extra == 'cbc'
Provides-Extra: glpk-mi
Requires-Dist: cvxopt>=1.3.0; extra == 'glpk-mi'
Provides-Extra: highs
Requires-Dist: cvxpy-base>=1.6.0; extra == 'highs'
Requires-Dist: highspy; extra == 'highs'
Provides-Extra: scip
Requires-Dist: pyscipopt; extra == 'scip'
